tests/__init__.py
tests/utils_test.py
tests/version_test.py
zetta/__init__.py
zetta/config_templates.py
zetta/job.py
zetta/main.py
zetta/_utils/async_utils.py
zetta/_utils/blockchain.py
zetta/_utils/cli_options.py
zetta/_utils/connections.py
zetta/_utils/logger.py
zetta/_utils/profile.py
zetta/_utils/abi/zetta.py
zetta/cli/__init__.py
zetta/cli/billing.py
zetta/cli/chain.py
zetta/cli/databases_v2.py
zetta/cli/dataset.py
zetta/cli/datasets_v2.py
zetta/cli/entry_point.py
zetta/cli/example.py
zetta/cli/github.py
zetta/cli/huggingface.py
zetta/cli/job.py
zetta/cli/marketplace.py
zetta/cli/model.py
zetta/cli/profile.py
zetta/cli/rewards.py
zetta/cli/run.py
zetta/cli/secret.py
zetta/cli/serving.py
zetta/cli/setup.py
zetta/cli/storage.py
zetta/cli/utils.py
zetta/cli/wallet.py
zetta_version/__init__.py
zetta_version/__main__.py
zetta_version/__version_generated.py
zetta-0.0.113.dist-info/METADATA
zetta-0.0.113.dist-info/WHEEL
zetta-0.0.113.dist-info/entry_points.txt
zetta-0.0.113.dist-info/top_level.txt
zetta-0.0.113.dist-info/RECORD
