Metadata-Version: 2.1
Name: zetta
Version: 0.0.113
Summary: Python client library for ZettaBlock AI Network
Author: ZettaBlock Labs
Author-email: support@zettablock.com
Project-URL: Homepage, https://zettablock.com
Project-URL: Source, https://github.com/Zettablock/zetta-py-client
Keywords: zettablock,client,cloud,AI,blockchain,infrastructure
Classifier: Topic :: System :: Distributed Computing
Classifier: Operating System :: OS Independent
Classifier: License :: OSI Approved :: Apache Software License
Classifier: Programming Language :: Python :: 3
Requires-Python: >=3.9
Requires-Dist: click
Requires-Dist: typer
Requires-Dist: synchronicity (~=0.6.7)
Requires-Dist: openai
Requires-Dist: requests
Requires-Dist: termcolor
Requires-Dist: pyfiglet
Requires-Dist: PyYAML
Requires-Dist: web3
Requires-Dist: grpcio
Requires-Dist: grpcio-tools
Requires-Dist: pyiceberg
Requires-Dist: pyarrow
Requires-Dist: boto
Requires-Dist: boto3
Requires-Dist: botocore
